django_docmgr-0.7.0.dist-info/licenses/LICENSE.txt
docmgr/__init__.py
docmgr/admin.py
docmgr/app_settings.py
docmgr/apps.py
docmgr/conftest.py
docmgr/drf.py
docmgr/forms.py
docmgr/models.py
docmgr/permissions.py
docmgr/signals.py
docmgr/urls.py
docmgr/views.py
docmgr/widgets.py
docmgr/migrations/0001_initial.py
docmgr/migrations/0002_auto_20151031_2048.py
docmgr/migrations/0003_auto_20160225_0135.py
docmgr/migrations/0004_auto_20160228_0146.py
docmgr/migrations/0005_auto_20160409_1857.py
docmgr/migrations/0006_auto_20160415_2043.py
docmgr/migrations/0007_auto_20160415_2108.py
docmgr/migrations/0008_auto_20160420_0245.py
docmgr/migrations/0009_alter_document_docfile.py
docmgr/migrations/0010_alter_document_object_id.py
docmgr/migrations/__init__.py
docmgr/templatetags/__init__.py
docmgr/templatetags/docmgr_tags.py
docmgr/tests/test_docmgr.py
docmgr/tests/test_object_permissions.py
docmgr/tests/test_signals.py
django_docmgr-0.7.0.dist-info/METADATA
django_docmgr-0.7.0.dist-info/WHEEL
django_docmgr-0.7.0.dist-info/top_level.txt
django_docmgr-0.7.0.dist-info/RECORD
