Metadata-Version: 2.4
Name: django-docmgr
Version: 0.7.0
Summary: A pluggable Django app to reference documents (files) in models.
Author-email: Michael Heumann <normic@mailbox.org>
License: BSD-3-Clause License
Project-URL: Homepage, https://github.com/normic/django-docmgr
Project-URL: Repository, https://github.com/normic/django-docmgr.git
Project-URL: Issues, https://github.com/normic/django-docmgr/issues
Project-URL: Changelog, https://github.com/normic/django-docmgr/blob/master/CHANGELOG.md
Keywords: django,documents,files,contenttypes,drf,storage
Classifier: Development Status :: 4 - Beta
Classifier: Environment :: Web Environment
Classifier: Framework :: Django
Classifier: License :: OSI Approved :: BSD License
Classifier: Intended Audience :: Developers
Classifier: Operating System :: OS Independent
Classifier: Programming Language :: Python
Classifier: Programming Language :: Python :: 3
Classifier: Programming Language :: Python :: 3 :: Only
Classifier: Programming Language :: Python :: 3.10
Classifier: Programming Language :: Python :: 3.11
Classifier: Programming Language :: Python :: 3.12
Classifier: Topic :: Internet :: WWW/HTTP
Classifier: Topic :: Internet :: WWW/HTTP :: Dynamic Content
Requires-Python: >=3.10
License-File: LICENSE.txt
Requires-Dist: django>=4.2
Requires-Dist: django-braces>=1.8.1
Requires-Dist: django-downloadview>=2.4.0
Requires-Dist: djangorestframework-stubs>=3.16.6
Requires-Dist: pytest>=8.4.2
Requires-Dist: pytest-cov>=7.0.0
Provides-Extra: drf
Requires-Dist: djangorestframework>=3.14; extra == "drf"
Dynamic: license-file
